README.md
setup.py
wheelcode.py
wheelcode.egg-info/PKG-INFO
wheelcode.egg-info/SOURCES.txt
wheelcode.egg-info/dependency_links.txt
wheelcode.egg-info/top_level.txt